{"page":4,"total_pages":8,"items":[{"id":"TR00472","name":"Юбка BEFREE LITE 47","brand":"Befree","cat":"Юбка","price":2359,"price_old":2999,"color":null,"available":true},{"id":"TR00474","name":"Mango Street 12, цвет розовый","brand":"Mango","cat":"Сандалии","price":10659,"price_old":null,"color":"розовый","available":true},{"id":"TR00477","name":"Джинсы LACOSTE ESSENTIAL","brand":"Lacoste","cat":"Джинсы","price":9739,"price_old":null,"color":null,"available":false},{"id":"TR00480","name":"Ботинки Reebok, зелёный","brand":"Reebok","cat":"Ботинки","price":9299,"price_old":12869,"color":"зелёный","available":true},{"id":"TR00483","name":"Юбка Lacoste Max, белый","brand":"Lacoste","cat":"Юбка","price":1279,"price_old":null,"color":null,"available":true},{"id":"TR00484","name":"Футболка New Balance замша","brand":"New Balance","cat":"Футболка","price":3159,"price_old":4359,"color":"хаки","available":true},{"id":"TR00485","name":"Кеды PUMA BASIC 70","brand":"Puma","cat":"Кеды","price":20659,"price_old":null,"color":"бежевый","available":true},{"id":"TR00486","name":"O'STIN Sport — сумка (синий)","brand":"O'STIN","cat":"Сумка","price":1249,"price_old":1629,"color":"синий","available":false},{"id":"TR00488","name":"Кеды Guess Flex 37, зелёный","brand":"Guess","cat":"Кеды","price":5689,"price_old":null,"color":"зелёный","available":true},{"id":"TR00493","name":"Очки Tom Tailor деним","brand":"Tom Tailor","cat":"Очки","price":5979,"price_old":7449,"color":"чёрный","available":true},{"id":"TR00495","name":"худи zarina premium, белый хит","brand":"Zarina","cat":"Худи","price":6749,"price_old":null,"color":"белый","available":true},{"id":"TR00498","name":"Платье Converse / синий, кожа","brand":null,"cat":"Платье","price":2249,"price_old":3369,"color":"синий","available":true},{"id":"TR00499","name":"Ботинки The North Face Essential 82, белый","brand":"The North Face","cat":"Ботинки","price":4629,"price_old":null,"color":null,"available":false},{"id":"TR00502","name":"кеды adidas / бежевый, кожа","brand":"adidas","cat":"Кеды","price":15169,"price_old":17739,"color":"бежевый","available":true},{"id":"TR00504","name":"ботинки tom tailor classic, черный оригинал","brand":"Tom Tailor","cat":"Ботинки","price":15289,"price_old":null,"color":"чёрный","available":true},{"id":"TR00513","name":"Туфли Columbia Street 92, зелёный","brand":"Columbia","cat":"Туфли","price":6489,"price_old":null,"color":"зелёный","available":true},{"id":"TR00518","name":"Куртка adidas деним","brand":"adidas","cat":"Куртка","price":8279,"price_old":null,"color":null,"available":true},{"id":"TR00519","name":"Куртка adidas Retro, красный","brand":"adidas","cat":"Куртка","price":15139,"price_old":21759,"color":"красный","available":true},{"id":"TR00521","name":"Очки Converse Basic 48, бордовый","brand":null,"cat":"Очки","price":8169,"price_old":9929,"color":"бордовый","available":true},{"id":"TR00523","name":"Куртка Befree Lite 51, розовый","brand":"Befree","cat":"Куртка","price":1839,"price_old":null,"color":"розовый","available":true},{"id":"TR00524","name":"Ботинки Mango Max, голубой","brand":"Mango","cat":"Ботинки","price":5579,"price_old":null,"color":"голубой","available":true},{"id":"TR00527","name":"Ботинки GAP SPORT 75","brand":"GAP","cat":"Ботинки","price":16459,"price_old":23319,"color":"коричневый","available":false},{"id":"TR00536","name":"Футболка Reebok Sport 14, хаки","brand":"Reebok","cat":"Футболка","price":6919,"price_old":9739,"color":null,"available":true},{"id":"TR00537","name":"Туфли NEW BALANCE CITY","brand":"New Balance","cat":"Туфли","price":15719,"price_old":null,"color":"розовый","available":true},{"id":"TR00543","name":"Tom Tailor Pro, цвет белый","brand":null,"cat":"Ботинки","price":14749,"price_old":null,"color":null,"available":true},{"id":"TR00544","name":"Юбка Tom Tailor Original 37, голубой","brand":null,"cat":"Юбка","price":13729,"price_old":null,"color":"голубой","available":true},{"id":"TR00545","name":"Шапка Vans Sport 30, розовый","brand":"Vans","cat":"Шапка","price":4379,"price_old":null,"color":null,"available":true},{"id":"TR00547","name":"Сумка GAP Flex, зелёный","brand":"GAP","cat":"Сумка","price":9859,"price_old":11759,"color":"зелёный","available":false},{"id":"TR00551","name":"туфли guess retro, черный","brand":"Guess","cat":"Туфли","price":15169,"price_old":null,"color":null,"available":true},{"id":"TR00561","name":"сандалии adidas essential, красный новинка 2026","brand":"adidas","cat":"Сандалии","price":3049,"price_old":null,"color":null,"available":true},{"id":"TR00563","name":"Calvin Klein Air — ботинки (голубой)","brand":"Calvin Klein","cat":"Ботинки","price":11829,"price_old":null,"color":null,"available":false},{"id":"TR00564","name":"Сумка The North Face, голубой","brand":"The North Face","cat":"Сумка","price":5359,"price_old":null,"color":"голубой","available":true},{"id":"TR00565","name":"Шапка New Balance текстиль","brand":"New Balance","cat":"Шапка","price":7649,"price_old":null,"color":"белый","available":true},{"id":"TR00566","name":"очки puma шерсть","brand":"Puma","cat":"Очки","price":949,"price_old":null,"color":"голубой","available":true},{"id":"TR00568","name":"O'STIN Flex 69, цвет хаки","brand":"O'STIN","cat":"Ремень","price":3669,"price_old":null,"color":"хаки","available":false},{"id":"TR00569","name":"Свитер Levi's Basic, синий sale","brand":null,"cat":"Свитер","price":8219,"price_old":null,"color":"синий","available":true},{"id":"TR00577","name":"Туфли Vans Street 27, серый","brand":"Vans","cat":"Туфли","price":6319,"price_old":null,"color":"серый","available":true},{"id":"TR00580","name":"Джинсы Reebok Pro 66, серый","brand":null,"cat":"Джинсы","price":8599,"price_old":10489,"color":"серый","available":false},{"id":"TR00584","name":"Lacoste Classic 91 — юбка (бежевый)","brand":"Lacoste","cat":"Юбка","price":9539,"price_old":12209,"color":"бежевый","available":true},{"id":"TR00585","name":"Сандалии BEFREE URBAN 71","brand":"Befree","cat":"Сандалии","price":9139,"price_old":13659,"color":"розовый","available":true},{"id":"TR00588","name":"Ботинки adidas Sport, белый","brand":null,"cat":"Ботинки","price":11289,"price_old":13599,"color":"белый","available":false},{"id":"TR00590","name":"the north face sport — юбка (голубой)","brand":"The North Face","cat":"Юбка","price":4309,"price_old":null,"color":"голубой","available":true},{"id":"TR00592","name":"Ремень CONVERSE URBAN 19","brand":"Converse","cat":"Ремень","price":3529,"price_old":null,"color":"бежевый","available":true},{"id":"TR00595","name":"Ботинки Guess Sport, голубой","brand":"Guess","cat":"Ботинки","price":15719,"price_old":null,"color":"голубой","available":true},{"id":"TR00596","name":"Очки New Balance Original 94, бордовый","brand":"New Balance","cat":"Очки","price":2879,"price_old":null,"color":"бордовый","available":true},{"id":"TR00601","name":"Джинсы Tom Tailor текстиль","brand":null,"cat":"Джинсы","price":8939,"price_old":null,"color":"белый","available":true},{"id":"TR00602","name":"Платье New Balance Essential 88, чёрный sale","brand":"New Balance","cat":"Платье","price":1439,"price_old":null,"color":"чёрный","available":true},{"id":"TR00605","name":"Рюкзак Nike Max 67, бордовый","brand":"Nike","cat":"Рюкзак","price":9329,"price_old":13049,"color":"бордовый","available":true},{"id":"TR00606","name":"кеды guess urban 79, розовый","brand":"Guess","cat":"Кеды","price":5299,"price_old":null,"color":null,"available":false},{"id":"TR00608","name":"adidas Urban — кеды (синий)","brand":null,"cat":"Кеды","price":9139,"price_old":12099,"color":"синий","available":true}]}
