{"ts":"2026-07-09T19:17:00Z","rows":[{"sku":"LMD-000094","title":"Шапка Nike City, коричневый","own":9549,"min_comp":7249,"offers":2,"gap_pct":31.7},{"sku":"LMD-000774","title":"Куртка Vans Sport 93, коричневый","own":13329,"min_comp":11229,"offers":1,"gap_pct":18.7},{"sku":"LMD-000308","title":"Кеды Vans Basic 96, синий","own":5509,"min_comp":4709,"offers":1,"gap_pct":17.0},{"sku":"LMD-000204","title":"Худи Levi's Street, розовый","own":8019,"min_comp":6859,"offers":3,"gap_pct":16.9},{"sku":"LMD-000460","title":"Рюкзак The North Face Classic 24, серый","own":3819,"min_comp":3269,"offers":1,"gap_pct":16.8},{"sku":"LMD-000682","title":"Туфли Nike Street 74, бордовый","own":11939,"min_comp":10239,"offers":1,"gap_pct":16.6},{"sku":"LMD-000794","title":"Ремень Lacoste Sport, бордовый","own":9169,"min_comp":7869,"offers":2,"gap_pct":16.5},{"sku":"LMD-000280","title":"Очки Lacoste Pro, синий","own":7559,"min_comp":6489,"offers":1,"gap_pct":16.5},{"sku":"LMD-000562","title":"Туфли Converse Max 49, хаки","own":14389,"min_comp":12359,"offers":1,"gap_pct":16.4},{"sku":"LMD-000008","title":"Кеды Befree Lite 33, красный","own":11349,"min_comp":9759,"offers":2,"gap_pct":16.3},{"sku":"LMD-000330","title":"Очки Tommy Hilfiger Max 70, розовый","own":4129,"min_comp":3549,"offers":1,"gap_pct":16.3},{"sku":"LMD-000409","title":"Шапка Befree Pro 52, чёрный","own":6419,"min_comp":5519,"offers":2,"gap_pct":16.3},{"sku":"LMD-000560","title":"Сандалии Puma Air, коричневый","own":8279,"min_comp":7119,"offers":1,"gap_pct":16.3},{"sku":"LMD-000718","title":"Кроссовки GAP Street 95, хаки","own":9679,"min_comp":8329,"offers":1,"gap_pct":16.2},{"sku":"LMD-000530","title":"Рюкзак Converse Premium, чёрный","own":7729,"min_comp":6659,"offers":1,"gap_pct":16.1},{"sku":"LMD-000214","title":"Худи Tommy Hilfiger Lite 68, белый","own":11699,"min_comp":10089,"offers":2,"gap_pct":16.0},{"sku":"LMD-000451","title":"Джинсы Nike City 34, бордовый","own":3429,"min_comp":2959,"offers":2,"gap_pct":15.9},{"sku":"LMD-000761","title":"Ботинки GAP Premium 59, серый","own":4949,"min_comp":4269,"offers":1,"gap_pct":15.9},{"sku":"LMD-000402","title":"Джинсы Calvin Klein Original 84, белый","own":4839,"min_comp":4179,"offers":3,"gap_pct":15.8},{"sku":"LMD-000258","title":"Брюки Befree Pro, голубой","own":10059,"min_comp":8689,"offers":1,"gap_pct":15.8},{"sku":"LMD-000843","title":"Сумка New Balance Street, коричневый","own":9199,"min_comp":7969,"offers":1,"gap_pct":15.4},{"sku":"LMD-000190","title":"Пальто Levi's Pro, красный","own":11009,"min_comp":9549,"offers":2,"gap_pct":15.3},{"sku":"LMD-000900","title":"Ремень Nike Street 76, бежевый","own":5809,"min_comp":5039,"offers":3,"gap_pct":15.3},{"sku":"LMD-000107","title":"Сумка Nike Retro, серый","own":6749,"min_comp":5859,"offers":1,"gap_pct":15.2},{"sku":"LMD-000450","title":"Кеды Nike Max 35, бежевый","own":15919,"min_comp":13829,"offers":3,"gap_pct":15.1},{"sku":"LMD-000169","title":"Рюкзак Zarina Flex 36, голубой","own":1529,"min_comp":1329,"offers":2,"gap_pct":15.0},{"sku":"LMD-000430","title":"Пальто Vans Premium, бежевый","own":3679,"min_comp":3199,"offers":1,"gap_pct":15.0},{"sku":"LMD-000740","title":"Ботинки O'STIN Pro 47, белый","own":5149,"min_comp":4479,"offers":2,"gap_pct":15.0},{"sku":"LMD-000753","title":"Туфли Reebok Basic, серый","own":7299,"min_comp":6349,"offers":2,"gap_pct":15.0},{"sku":"LMD-000185","title":"Сумка Vans Classic, красный","own":6989,"min_comp":6089,"offers":1,"gap_pct":14.8},{"sku":"LMD-000639","title":"Пальто New Balance Retro, голубой","own":12379,"min_comp":10779,"offers":1,"gap_pct":14.8},{"sku":"LMD-000135","title":"Платье The North Face Air, белый","own":3239,"min_comp":2829,"offers":2,"gap_pct":14.5},{"sku":"LMD-000813","title":"Сандалии Columbia Lite 82, чёрный","own":13699,"min_comp":11979,"offers":2,"gap_pct":14.4},{"sku":"LMD-000024","title":"Шапка Converse Max, красный","own":799,"min_comp":699,"offers":2,"gap_pct":14.3},{"sku":"LMD-000068","title":"Футболка Levi's Classic, хаки","own":5799,"min_comp":5079,"offers":2,"gap_pct":14.2},{"sku":"LMD-000695","title":"Кеды Levi's Pro, белый","own":16289,"min_comp":14269,"offers":1,"gap_pct":14.2},{"sku":"LMD-000731","title":"Кеды Levi's Essential, зелёный","own":3489,"min_comp":3059,"offers":2,"gap_pct":14.1},{"sku":"LMD-000756","title":"Рубашка Lacoste Air, синий","own":14599,"min_comp":12799,"offers":2,"gap_pct":14.1},{"sku":"LMD-000849","title":"Платье Zarina Street 17, чёрный","own":15539,"min_comp":13629,"offers":1,"gap_pct":14.0},{"sku":"LMD-000434","title":"Сумка O'STIN Street, хаки","own":4569,"min_comp":4009,"offers":1,"gap_pct":14.0},{"sku":"LMD-000480","title":"Ботинки Reebok City, зелёный","own":8429,"min_comp":7399,"offers":3,"gap_pct":13.9},{"sku":"LMD-000584","title":"Юбка Lacoste Classic 91, бежевый","own":8839,"min_comp":7759,"offers":2,"gap_pct":13.9},{"sku":"LMD-000158","title":"Рюкзак Tommy Hilfiger Lite 34, коричневый","own":1649,"min_comp":1449,"offers":1,"gap_pct":13.8},{"sku":"LMD-000679","title":"Рюкзак Reebok Retro, хаки","own":4199,"min_comp":3689,"offers":1,"gap_pct":13.8},{"sku":"LMD-000194","title":"Футболка Reebok City, красный","own":10539,"min_comp":9269,"offers":2,"gap_pct":13.7},{"sku":"LMD-000197","title":"Худи Befree Pro, хаки","own":10519,"min_comp":9249,"offers":3,"gap_pct":13.7},{"sku":"LMD-000003","title":"Сандалии Lacoste Lite 73, синий","own":18679,"min_comp":16429,"offers":1,"gap_pct":13.7},{"sku":"LMD-000233","title":"Свитер Lacoste Basic 63, красный","own":7479,"min_comp":6579,"offers":2,"gap_pct":13.7},{"sku":"LMD-000635","title":"Кроссовки Columbia Air, красный","own":5479,"min_comp":4829,"offers":3,"gap_pct":13.5},{"sku":"LMD-000533","title":"Футболка Vans Max 5, хаки","own":9639,"min_comp":8489,"offers":1,"gap_pct":13.5},{"sku":"LMD-000388","title":"Кеды adidas Lite, хаки","own":13719,"min_comp":12109,"offers":2,"gap_pct":13.3},{"sku":"LMD-000389","title":"Кроссовки Levi's Pro, серый","own":18949,"min_comp":16719,"offers":3,"gap_pct":13.3},{"sku":"LMD-000079","title":"Свитер Nike Premium, белый","own":14749,"min_comp":13029,"offers":2,"gap_pct":13.2},{"sku":"LMD-000314","title":"Пальто Befree Urban, бежевый","own":13409,"min_comp":11849,"offers":1,"gap_pct":13.2},{"sku":"LMD-000205","title":"Платье adidas City 24, красный","own":15809,"min_comp":18189,"offers":1,"gap_pct":-13.1},{"sku":"LMD-000503","title":"Ботинки New Balance Classic, бежевый","own":3189,"min_comp":2819,"offers":2,"gap_pct":13.1},{"sku":"LMD-000831","title":"Шапка Nike City, красный","own":7529,"min_comp":6659,"offers":3,"gap_pct":13.1},{"sku":"LMD-000523","title":"Куртка Befree Lite 51, розовый","own":1819,"min_comp":1609,"offers":2,"gap_pct":13.1},{"sku":"LMD-000071","title":"Туфли Guess City 26, чёрный","own":16139,"min_comp":14279,"offers":2,"gap_pct":13.0},{"sku":"LMD-000329","title":"Рюкзак Tommy Hilfiger Lite, зелёный","own":7659,"min_comp":6779,"offers":2,"gap_pct":13.0},{"sku":"LMD-000785","title":"Рюкзак Reebok Street 97, бордовый","own":1479,"min_comp":1309,"offers":2,"gap_pct":13.0},{"sku":"LMD-000594","title":"Очки GAP Lite, голубой","own":8649,"min_comp":7659,"offers":1,"gap_pct":12.9},{"sku":"LMD-000625","title":"Туфли Reebok City, бежевый","own":4889,"min_comp":4329,"offers":1,"gap_pct":12.9},{"sku":"LMD-000507","title":"Сумка Zarina Basic, зелёный","own":3189,"min_comp":3659,"offers":1,"gap_pct":-12.8},{"sku":"LMD-000724","title":"Шапка Zarina Sport 55, бордовый","own":6529,"min_comp":5789,"offers":2,"gap_pct":12.8},{"sku":"LMD-000879","title":"Ремень Nike Pro, белый","own":1849,"min_comp":1639,"offers":3,"gap_pct":12.8},{"sku":"LMD-000791","title":"Джинсы GAP Max, чёрный","own":5499,"min_comp":4879,"offers":3,"gap_pct":12.7},{"sku":"LMD-000728","title":"Куртка Puma Premium 26, чёрный","own":3719,"min_comp":3299,"offers":1,"gap_pct":12.7},{"sku":"LMD-000085","title":"Рубашка Tom Tailor Street, синий","own":4439,"min_comp":5079,"offers":1,"gap_pct":-12.6},{"sku":"LMD-000417","title":"Футболка Puma Air, хаки","own":2149,"min_comp":2459,"offers":1,"gap_pct":-12.6},{"sku":"LMD-000593","title":"Кроссовки adidas Urban, синий","own":13099,"min_comp":11629,"offers":2,"gap_pct":12.6},{"sku":"LMD-000784","title":"Ботинки New Balance Basic, чёрный","own":13449,"min_comp":11959,"offers":2,"gap_pct":12.5},{"sku":"LMD-000839","title":"Кеды Befree Essential 84, красный","own":7659,"min_comp":6809,"offers":2,"gap_pct":12.5},{"sku":"LMD-000448","title":"Сумка Nike Street 76, серый","own":1979,"min_comp":1759,"offers":1,"gap_pct":12.5},{"sku":"LMD-000720","title":"Шапка New Balance Pro, бежевый","own":2889,"min_comp":2569,"offers":1,"gap_pct":12.5},{"sku":"LMD-000519","title":"Куртка adidas Retro, красный","own":14599,"min_comp":12989,"offers":2,"gap_pct":12.4},{"sku":"LMD-000863","title":"Свитер Reebok Essential 95, серый","own":11779,"min_comp":10479,"offers":1,"gap_pct":12.4},{"sku":"LMD-000139","title":"Очки Columbia Lite 93, бежевый","own":6329,"min_comp":7219,"offers":1,"gap_pct":-12.3},{"sku":"LMD-000298","title":"Ремень Tom Tailor Flex 1, белый","own":9059,"min_comp":10329,"offers":1,"gap_pct":-12.3},{"sku":"LMD-000638","title":"Кроссовки Puma Max 35, серый","own":5419,"min_comp":6179,"offers":1,"gap_pct":-12.3}],"coverage":0.7956,"competitiveness":0.3743}
