{"queue":[{"key":"style-hub:UST00002","sku":"LMD-000128","score":0.5324,"queued_at":"2026-07-11T10:36:12Z"},{"key":"style-hub:UST00036","sku":"LMD-000373","score":0.5271,"queued_at":"2026-07-08T13:17:00Z"},{"key":"trend-api:UTR00047","sku":"LMD-000347","score":0.5259,"queued_at":"2026-07-10T09:55:40Z"},{"key":"trend-api:UTR00027","sku":"LMD-000900","score":0.524,"queued_at":"2026-07-09T01:17:00Z"},{"key":"moda-market:UMO00029","sku":"LMD-000860","score":0.5194,"queued_at":"2026-07-10T03:21:38Z"},{"key":"trend-api:UTR00031","sku":"LMD-000303","score":0.5174,"queued_at":"2026-07-09T01:17:00Z"},{"key":"moda-market:UMO00016","sku":"LMD-000080","score":0.5172,"queued_at":"2026-07-11T10:36:12Z"},{"key":"style-hub:UST00020","sku":"LMD-000184","score":0.5168,"queued_at":"2026-07-08T13:17:00Z"},{"key":"trend-api:UTR00008","sku":"LMD-000314","score":0.5166,"queued_at":"2026-07-07T19:17:00Z"},{"key":"moda-market:UMO00046","sku":"LMD-000549","score":0.5156,"queued_at":"2026-07-10T03:21:38Z"},{"key":"moda-market:UMO00025","sku":"LMD-000109","score":0.5145,"queued_at":"2026-07-11T10:36:12Z"},{"key":"moda-market:UMO00034","sku":"LMD-000893","score":0.5133,"queued_at":"2026-07-07T19:17:00Z"},{"key":"moda-market:UMO00053","sku":"LMD-000862","score":0.5125,"queued_at":"2026-07-07T19:17:00Z"},{"key":"style-hub:UST00014","sku":"LMD-000617","score":0.5124,"queued_at":"2026-07-08T19:17:00Z"},{"key":"moda-market:UMO00003","sku":"LMD-000741","score":0.5119,"queued_at":"2026-07-07T19:17:00Z"},{"key":"moda-market:UMO00044","sku":"LMD-000024","score":0.5113,"queued_at":"2026-07-07T19:17:00Z"},{"key":"moda-market:UMO00042","sku":"LMD-000549","score":0.5102,"queued_at":"2026-07-07T19:17:00Z"},{"key":"trend-api:UTR00048","sku":"LMD-000823","score":0.5101,"queued_at":"2026-07-06T01:17:00Z"},{"key":"trend-api:UTR00004","sku":"LMD-000112","score":0.5097,"queued_at":"2026-07-10T03:21:38Z"},{"key":"trend-api:UTR00052","sku":"LMD-000277","score":0.5096,"queued_at":"2026-07-07T01:17:00Z"},{"key":"trend-api:UTR00022","sku":"LMD-000297","score":0.5096,"queued_at":"2026-07-08T01:17:00Z"},{"key":"trend-api:UTR00015","sku":"LMD-000245","score":0.5077,"queued_at":"2026-07-06T01:17:00Z"},{"key":"trend-api:UTR00019","sku":"LMD-000153","score":0.507,"queued_at":"2026-07-02T19:17:00Z"},{"key":"moda-market:UMO00037","sku":"LMD-000636","score":0.507,"queued_at":"2026-07-07T19:17:00Z"},{"key":"style-hub:UST00030","sku":"LMD-000808","score":0.5053,"queued_at":"2026-07-05T13:17:00Z"},{"key":"trend-api:UTR00058","sku":"LMD-000059","score":0.505,"queued_at":"2026-07-03T01:17:00Z"},{"key":"trend-api:UTR00039","sku":"LMD-000163","score":0.5044,"queued_at":"2026-07-10T03:21:38Z"},{"key":"trend-api:UTR00054","sku":"LMD-000844","score":0.5042,"queued_at":"2026-07-07T19:17:00Z"},{"key":"trend-api:UTR00017","sku":"LMD-000048","score":0.5039,"queued_at":"2026-07-02T19:17:00Z"},{"key":"moda-market:UMO00008","sku":"LMD-000648","score":0.5025,"queued_at":"2026-07-09T21:38:37Z"},{"key":"trend-api:UTR00032","sku":"LMD-000290","score":0.5014,"queued_at":"2026-07-02T19:17:00Z"},{"key":"moda-market:UMO00051","sku":"LMD-000481","score":0.5006,"queued_at":"2026-07-07T19:17:00Z"},{"key":"trend-api:UTR00042","sku":"LMD-000042","score":0.5003,"queued_at":"2026-07-08T01:17:00Z"}],"confirmed":{"style-hub:ST00352":{"sku":"LMD-000352","method":"review","score":0.7341,"ts":"2026-07-04T19:17:00Z"},"trend-api:TR00675":{"sku":"LMD-000675","method":"review","score":0.8664,"ts":"2026-07-05T01:17:00Z"},"trend-api:TR00284":{"sku":"LMD-000284","method":"review","score":0.8188,"ts":"2026-07-05T01:17:00Z"},"trend-api:TR00725":{"sku":"LMD-000725","method":"review","score":0.7835,"ts":"2026-07-05T01:17:00Z"},"trend-api:TR00547":{"sku":"LMD-000547","method":"review","score":0.7342,"ts":"2026-07-05T01:17:00Z"},"trend-api:TR00635":{"sku":"LMD-000635","method":"review","score":0.7339,"ts":"2026-07-05T01:17:00Z"},"style-hub:ST00798":{"sku":"LMD-000798","method":"review","score":0.718,"ts":"2026-07-05T01:17:00Z"},"trend-api:TR00313":{"sku":"LMD-000313","method":"review","score":0.712,"ts":"2026-07-05T01:17:00Z"},"style-hub:ST00020":{"sku":"LMD-000020","method":"review","score":0.73,"ts":"2026-07-05T07:17:00Z"},"trend-api:UTR00010":{"sku":"LMD-000094","method":"review","score":0.5404,"ts":"2026-07-05T07:17:00Z"},"style-hub:ST00629":{"sku":"LMD-000629","method":"review","score":0.808,"ts":"2026-07-05T13:17:00Z"},"style-hub:UST00007":{"sku":"LMD-000753","method":"review","score":0.5567,"ts":"2026-07-05T19:17:00Z"},"style-hub:ST00551":{"sku":"LMD-000551","method":"review","score":0.8535,"ts":"2026-07-06T01:17:00Z"},"style-hub:ST00117":{"sku":"LMD-000117","method":"review","score":0.8117,"ts":"2026-07-06T01:17:00Z"},"trend-api:TR00523":{"sku":"LMD-000523","method":"review","score":0.7385,"ts":"2026-07-06T01:17:00Z"},"trend-api:TR00290":{"sku":"LMD-000290","method":"review","score":0.7305,"ts":"2026-07-06T01:17:00Z"},"style-hub:ST00743":{"sku":"LMD-000743","method":"review","score":0.7029,"ts":"2026-07-06T01:17:00Z"},"style-hub:ST00260":{"sku":"LMD-000260","method":"review","score":0.8904,"ts":"2026-07-07T01:17:00Z"},"style-hub:ST00090":{"sku":"LMD-000090","method":"review","score":0.7856,"ts":"2026-07-07T01:17:00Z"},"style-hub:ST00458":{"sku":"LMD-000458","method":"review","score":0.7397,"ts":"2026-07-07T01:17:00Z"},"style-hub:ST00124":{"sku":"LMD-000124","method":"review","score":0.7189,"ts":"2026-07-07T01:17:00Z"},"style-hub:ST00615":{"sku":"LMD-000615","method":"review","score":0.7144,"ts":"2026-07-07T01:17:00Z"},"moda-market:MO00594":{"sku":"LMD-000594","method":"review","score":0.847,"ts":"2026-07-07T19:17:00Z"},"moda-market:MO00406":{"sku":"LMD-000406","method":"review","score":0.7685,"ts":"2026-07-07T19:17:00Z"},"moda-market:MO00886":{"sku":"LMD-000886","method":"review","score":0.7395,"ts":"2026-07-07T19:17:00Z"},"moda-market:MO00228":{"sku":"LMD-000228","method":"review","score":0.736,"ts":"2026-07-07T19:17:00Z"},"moda-market:MO00439":{"sku":"LMD-000439","method":"review","score":0.7305,"ts":"2026-07-07T19:17:00Z"},"moda-market:MO00393":{"sku":"LMD-000393","method":"review","score":0.7289,"ts":"2026-07-07T19:17:00Z"},"moda-market:MO00578":{"sku":"LMD-000578","method":"review","score":0.7288,"ts":"2026-07-07T19:17:00Z"},"moda-market:MO00044":{"sku":"LMD-000044","method":"review","score":0.7284,"ts":"2026-07-07T19:17:00Z"},"moda-market:MO00697":{"sku":"LMD-000697","method":"review","score":0.7254,"ts":"2026-07-07T19:17:00Z"},"moda-market:MO00510":{"sku":"LMD-000510","method":"review","score":0.7252,"ts":"2026-07-07T19:17:00Z"},"moda-market:MO00414":{"sku":"LMD-000414","method":"review","score":0.724,"ts":"2026-07-07T19:17:00Z"},"moda-market:MO00850":{"sku":"LMD-000850","method":"review","score":0.7209,"ts":"2026-07-07T19:17:00Z"},"moda-market:MO00305":{"sku":"LMD-000305","method":"review","score":0.7208,"ts":"2026-07-07T19:17:00Z"},"style-hub:ST00561":{"sku":"LMD-000561","method":"review","score":0.718,"ts":"2026-07-07T19:17:00Z"},"moda-market:MO00643":{"sku":"LMD-000643","method":"review","score":0.718,"ts":"2026-07-07T19:17:00Z"},"moda-market:MO00568":{"sku":"LMD-000568","method":"review","score":0.7114,"ts":"2026-07-07T19:17:00Z"},"moda-market:MO00859":{"sku":"LMD-000859","method":"review","score":0.7091,"ts":"2026-07-07T19:17:00Z"},"moda-market:MO00545":{"sku":"LMD-000545","method":"review","score":0.7033,"ts":"2026-07-07T19:17:00Z"},"moda-market:MO00068":{"sku":"LMD-000068","method":"review","score":0.6695,"ts":"2026-07-07T19:17:00Z"},"trend-api:TR00551":{"sku":"LMD-000551","method":"review","score":0.8613,"ts":"2026-07-08T01:17:00Z"},"moda-market:MO00038":{"sku":"LMD-000038","method":"review","score":0.8494,"ts":"2026-07-08T01:17:00Z"},"style-hub:ST00842":{"sku":"LMD-000842","method":"review","score":0.8333,"ts":"2026-07-08T01:17:00Z"},"moda-market:MO00538":{"sku":"LMD-000538","method":"review","score":0.7486,"ts":"2026-07-08T01:17:00Z"},"moda-market:MO00630":{"sku":"LMD-000630","method":"review","score":0.7398,"ts":"2026-07-08T01:17:00Z"},"moda-market:MO00857":{"sku":"LMD-000857","method":"review","score":0.7361,"ts":"2026-07-08T01:17:00Z"},"moda-market:MO00671":{"sku":"LMD-000671","method":"review","score":0.7311,"ts":"2026-07-08T01:17:00Z"},"moda-market:MO00673":{"sku":"LMD-000673","method":"review","score":0.731,"ts":"2026-07-08T01:17:00Z"},"moda-market:MO00566":{"sku":"LMD-000566","method":"review","score":0.7298,"ts":"2026-07-08T01:17:00Z"},"moda-market:MO00265":{"sku":"LMD-000265","method":"review","score":0.7271,"ts":"2026-07-08T01:17:00Z"},"moda-market:MO00641":{"sku":"LMD-000641","method":"review","score":0.7271,"ts":"2026-07-08T01:17:00Z"},"moda-market:MO00824":{"sku":"LMD-000824","method":"review","score":0.7199,"ts":"2026-07-08T01:17:00Z"},"moda-market:MO00562":{"sku":"LMD-000562","method":"review","score":0.719,"ts":"2026-07-08T01:17:00Z"},"moda-market:MO00368":{"sku":"LMD-000368","method":"review","score":0.7175,"ts":"2026-07-08T01:17:00Z"},"moda-market:MO00461":{"sku":"LMD-000461","method":"review","score":0.7171,"ts":"2026-07-08T01:17:00Z"},"moda-market:MO00137":{"sku":"LMD-000137","method":"review","score":0.7167,"ts":"2026-07-08T01:17:00Z"},"moda-market:MO00452":{"sku":"LMD-000452","method":"review","score":0.716,"ts":"2026-07-08T01:17:00Z"},"moda-market:MO00554":{"sku":"LMD-000554","method":"review","score":0.7118,"ts":"2026-07-08T01:17:00Z"},"moda-market:MO00618":{"sku":"LMD-000618","method":"review","score":0.7092,"ts":"2026-07-08T01:17:00Z"},"moda-market:MO00615":{"sku":"LMD-000615","method":"review","score":0.7067,"ts":"2026-07-08T01:17:00Z"},"moda-market:MO00096":{"sku":"LMD-000096","method":"review","score":0.6989,"ts":"2026-07-08T01:17:00Z"},"style-hub:ST00450":{"sku":"LMD-000450","method":"review","score":0.7521,"ts":"2026-07-08T07:17:00Z"},"moda-market:MO00600":{"sku":"LMD-000600","method":"review","score":0.7351,"ts":"2026-07-08T07:17:00Z"},"moda-market:UMO00013":{"sku":"LMD-000021","method":"review","score":0.6034,"ts":"2026-07-08T07:17:00Z"},"moda-market:MO00646":{"sku":"LMD-000646","method":"review","score":0.731,"ts":"2026-07-08T19:17:00Z"},"style-hub:ST00398":{"sku":"LMD-000398","method":"review","score":0.8898,"ts":"2026-07-09T01:17:00Z"},"style-hub:ST00710":{"sku":"LMD-000710","method":"review","score":0.8625,"ts":"2026-07-09T01:17:00Z"},"style-hub:ST00805":{"sku":"LMD-000805","method":"review","score":0.8483,"ts":"2026-07-09T01:17:00Z"},"trend-api:TR00536":{"sku":"LMD-000536","method":"review","score":0.8214,"ts":"2026-07-09T01:17:00Z"},"moda-market:MO00480":{"sku":"LMD-000480","method":"review","score":0.8124,"ts":"2026-07-09T01:17:00Z"},"trend-api:TR00868":{"sku":"LMD-000868","method":"review","score":0.8026,"ts":"2026-07-09T01:17:00Z"},"moda-market:MO00028":{"sku":"LMD-000028","method":"review","score":0.7579,"ts":"2026-07-09T01:17:00Z"},"moda-market:MO00868":{"sku":"LMD-000868","method":"review","score":0.7391,"ts":"2026-07-09T01:17:00Z"},"style-hub:ST00778":{"sku":"LMD-000778","method":"review","score":0.7389,"ts":"2026-07-09T01:17:00Z"},"moda-market:MO00367":{"sku":"LMD-000367","method":"review","score":0.7388,"ts":"2026-07-09T01:17:00Z"},"trend-api:TR00614":{"sku":"LMD-000614","method":"review","score":0.737,"ts":"2026-07-09T01:17:00Z"},"moda-market:MO00261":{"sku":"LMD-000261","method":"review","score":0.7335,"ts":"2026-07-09T01:17:00Z"},"style-hub:ST00522":{"sku":"LMD-000522","method":"review","score":0.7316,"ts":"2026-07-09T01:17:00Z"},"moda-market:MO00748":{"sku":"LMD-000748","method":"review","score":0.7314,"ts":"2026-07-09T01:17:00Z"},"moda-market:MO00593":{"sku":"LMD-000593","method":"review","score":0.7311,"ts":"2026-07-09T01:17:00Z"},"moda-market:MO00055":{"sku":"LMD-000055","method":"review","score":0.7308,"ts":"2026-07-09T01:17:00Z"},"moda-market:MO00875":{"sku":"LMD-000875","method":"review","score":0.7307,"ts":"2026-07-09T01:17:00Z"},"moda-market:MO00119":{"sku":"LMD-000119","method":"review","score":0.7294,"ts":"2026-07-09T01:17:00Z"},"moda-market:MO00719":{"sku":"LMD-000719","method":"review","score":0.7276,"ts":"2026-07-09T01:17:00Z"},"moda-market:MO00634":{"sku":"LMD-000634","method":"review","score":0.7233,"ts":"2026-07-09T01:17:00Z"},"moda-market:MO00625":{"sku":"LMD-000625","method":"review","score":0.7229,"ts":"2026-07-09T01:17:00Z"},"moda-market:MO00035":{"sku":"LMD-000035","method":"review","score":0.7225,"ts":"2026-07-09T01:17:00Z"},"moda-market:MO00280":{"sku":"LMD-000280","method":"review","score":0.7166,"ts":"2026-07-09T01:17:00Z"},"moda-market:MO00361":{"sku":"LMD-000361","method":"review","score":0.7159,"ts":"2026-07-09T01:17:00Z"},"moda-market:MO00434":{"sku":"LMD-000434","method":"review","score":0.7066,"ts":"2026-07-09T01:17:00Z"},"moda-market:MO00190":{"sku":"LMD-000190","method":"review","score":0.7006,"ts":"2026-07-09T01:17:00Z"},"moda-market:MO00644":{"sku":"LMD-000644","method":"review","score":0.6891,"ts":"2026-07-09T01:17:00Z"},"moda-market:MO00471":{"sku":"LMD-000471","method":"review","score":0.682,"ts":"2026-07-09T01:17:00Z"},"moda-market:MO00526":{"sku":"LMD-000526","method":"review","score":0.793,"ts":"2026-07-09T07:17:00Z"},"moda-market:MO00399":{"sku":"LMD-000399","method":"review","score":0.7262,"ts":"2026-07-09T07:17:00Z"},"style-hub:ST00401":{"sku":"LMD-000401","method":"review","score":0.8142,"ts":"2026-07-09T21:38:37Z"},"moda-market:MO00444":{"sku":"LMD-000444","method":"review","score":0.8196,"ts":"2026-07-10T03:21:38Z"},"moda-market:MO00031":{"sku":"LMD-000031","method":"review","score":0.7988,"ts":"2026-07-10T03:21:38Z"},"style-hub:ST00071":{"sku":"LMD-000071","method":"review","score":0.7489,"ts":"2026-07-10T03:21:38Z"},"moda-market:MO00494":{"sku":"LMD-000494","method":"review","score":0.738,"ts":"2026-07-10T03:21:38Z"},"moda-market:MO00777":{"sku":"LMD-000777","method":"review","score":0.7349,"ts":"2026-07-10T03:21:38Z"},"style-hub:ST00359":{"sku":"LMD-000359","method":"review","score":0.7347,"ts":"2026-07-10T03:21:38Z"},"moda-market:MO00814":{"sku":"LMD-000814","method":"review","score":0.7321,"ts":"2026-07-10T03:21:38Z"},"moda-market:MO00236":{"sku":"LMD-000236","method":"review","score":0.7299,"ts":"2026-07-10T03:21:38Z"},"moda-market:MO00718":{"sku":"LMD-000718","method":"review","score":0.7282,"ts":"2026-07-10T03:21:38Z"},"moda-market:MO00446":{"sku":"LMD-000446","method":"review","score":0.7247,"ts":"2026-07-10T03:21:38Z"},"moda-market:MO00191":{"sku":"LMD-000191","method":"review","score":0.7233,"ts":"2026-07-10T03:21:38Z"},"moda-market:MO00493":{"sku":"LMD-000493","method":"review","score":0.7185,"ts":"2026-07-10T03:21:38Z"},"moda-market:MO00547":{"sku":"LMD-000547","method":"review","score":0.7174,"ts":"2026-07-10T03:21:38Z"},"moda-market:MO00148":{"sku":"LMD-000148","method":"review","score":0.7168,"ts":"2026-07-10T03:21:38Z"},"moda-market:MO00308":{"sku":"LMD-000308","method":"review","score":0.7168,"ts":"2026-07-10T03:21:38Z"},"moda-market:MO00275":{"sku":"LMD-000275","method":"review","score":0.7154,"ts":"2026-07-10T03:21:38Z"},"trend-api:TR00499":{"sku":"LMD-000499","method":"review","score":0.7152,"ts":"2026-07-10T03:21:38Z"},"trend-api:TR00763":{"sku":"LMD-000763","method":"review","score":0.7139,"ts":"2026-07-10T03:21:38Z"},"moda-market:MO00540":{"sku":"LMD-000540","method":"review","score":0.7067,"ts":"2026-07-10T03:21:38Z"},"style-hub:UST00009":{"sku":"LMD-000779","method":"review","score":0.6253,"ts":"2026-07-10T03:21:38Z"},"moda-market:MO00336":{"sku":"LMD-000336","method":"review","score":0.7801,"ts":"2026-07-10T04:27:30Z"},"moda-market:MO00411":{"sku":"LMD-000411","method":"review","score":0.7254,"ts":"2026-07-10T04:27:30Z"},"trend-api:UTR00044":{"sku":"LMD-000396","method":"review","score":0.548,"ts":"2026-07-10T04:27:30Z"},"style-hub:ST00309":{"sku":"LMD-000309","method":"review","score":0.8316,"ts":"2026-07-10T09:55:40Z"},"moda-market:MO00213":{"sku":"LMD-000213","method":"review","score":0.7178,"ts":"2026-07-10T15:05:33Z"},"moda-market:MO00157":{"sku":"LMD-000157","method":"review","score":0.7399,"ts":"2026-07-10T17:12:49Z"},"moda-market:MO00071":{"sku":"LMD-000071","method":"review","score":0.7379,"ts":"2026-07-10T17:12:49Z"},"moda-market:MO00009":{"sku":"LMD-000009","method":"review","score":0.7334,"ts":"2026-07-10T17:12:49Z"},"moda-market:MO00664":{"sku":"LMD-000664","method":"review","score":0.6754,"ts":"2026-07-10T19:54:51Z"},"moda-market:MO00695":{"sku":"LMD-000695","method":"review","score":0.7786,"ts":"2026-07-10T22:27:34Z"},"moda-market:MO00079":{"sku":"LMD-000079","method":"review","score":0.734,"ts":"2026-07-10T22:27:34Z"},"moda-market:MO00220":{"sku":"LMD-000220","method":"review","score":0.7207,"ts":"2026-07-10T22:27:34Z"},"trend-api:TR00122":{"sku":"LMD-000122","method":"review","score":0.7112,"ts":"2026-07-10T22:27:34Z"},"moda-market:UMO00015":{"sku":"LMD-000778","method":"review","score":0.6207,"ts":"2026-07-10T22:27:34Z"},"moda-market:MO00267":{"sku":"LMD-000267","method":"review","score":0.8322,"ts":"2026-07-11T03:46:30Z"},"style-hub:ST00773":{"sku":"LMD-000773","method":"review","score":0.82,"ts":"2026-07-11T03:46:30Z"},"moda-market:MO00725":{"sku":"LMD-000725","method":"review","score":0.8135,"ts":"2026-07-11T03:46:30Z"},"moda-market:MO00403":{"sku":"LMD-000403","method":"review","score":0.799,"ts":"2026-07-11T03:46:30Z"},"moda-market:MO00556":{"sku":"LMD-000556","method":"review","score":0.7748,"ts":"2026-07-11T03:46:30Z"},"moda-market:MO00217":{"sku":"LMD-000217","method":"review","score":0.7397,"ts":"2026-07-11T03:46:30Z"},"moda-market:MO00810":{"sku":"LMD-000810","method":"review","score":0.7377,"ts":"2026-07-11T03:46:30Z"},"style-hub:ST00275":{"sku":"LMD-000275","method":"review","score":0.7345,"ts":"2026-07-11T03:46:30Z"},"moda-market:MO00154":{"sku":"LMD-000154","method":"review","score":0.7331,"ts":"2026-07-11T03:46:30Z"},"moda-market:MO00463":{"sku":"LMD-000463","method":"review","score":0.7319,"ts":"2026-07-11T03:46:30Z"},"moda-market:MO00088":{"sku":"LMD-000088","method":"review","score":0.7301,"ts":"2026-07-11T03:46:30Z"},"moda-market:MO00636":{"sku":"LMD-000636","method":"review","score":0.7291,"ts":"2026-07-11T03:46:30Z"},"trend-api:TR00543":{"sku":"LMD-000543","method":"review","score":0.7289,"ts":"2026-07-11T03:46:30Z"},"moda-market:MO00778":{"sku":"LMD-000778","method":"review","score":0.7287,"ts":"2026-07-11T03:46:30Z"},"moda-market:MO00103":{"sku":"LMD-000103","method":"review","score":0.7255,"ts":"2026-07-11T03:46:30Z"},"style-hub:ST00819":{"sku":"LMD-000819","method":"review","score":0.7249,"ts":"2026-07-11T03:46:30Z"},"moda-market:MO00677":{"sku":"LMD-000677","method":"review","score":0.7235,"ts":"2026-07-11T03:46:30Z"},"moda-market:MO00201":{"sku":"LMD-000201","method":"review","score":0.7183,"ts":"2026-07-11T03:46:30Z"},"moda-market:MO00099":{"sku":"LMD-000099","method":"review","score":0.7143,"ts":"2026-07-11T03:46:30Z"},"moda-market:MO00743":{"sku":"LMD-000743","method":"review","score":0.7118,"ts":"2026-07-11T03:46:30Z"},"moda-market:MO00335":{"sku":"LMD-000335","method":"review","score":0.703,"ts":"2026-07-11T03:46:30Z"},"moda-market:MO00315":{"sku":"LMD-000315","method":"review","score":0.6695,"ts":"2026-07-11T03:46:30Z"},"style-hub:ST00776":{"sku":"LMD-000776","method":"review","score":0.8248,"ts":"2026-07-11T08:16:31Z"},"moda-market:MO00247":{"sku":"LMD-000247","method":"review","score":0.7364,"ts":"2026-07-11T08:16:31Z"},"moda-market:MO00124":{"sku":"LMD-000124","method":"review","score":0.718,"ts":"2026-07-11T08:16:31Z"},"moda-market:MO00802":{"sku":"LMD-000802","method":"review","score":0.718,"ts":"2026-07-11T08:16:31Z"},"style-hub:UST00028":{"sku":"LMD-000287","method":"review","score":0.6163,"ts":"2026-07-11T08:16:31Z"},"moda-market:MO00665":{"sku":"LMD-000665","method":"review","score":0.732,"ts":"2026-07-11T10:36:12Z"},"moda-market:MO00303":{"sku":"LMD-000303","method":"review","score":0.7075,"ts":"2026-07-11T10:36:12Z"},"moda-market:MO00102":{"sku":"LMD-000102","method":"review","score":0.6987,"ts":"2026-07-11T10:36:12Z"},"moda-market:MO00080":{"sku":"LMD-000080","method":"review","score":0.7369,"ts":"2026-07-11T13:57:37Z"},"moda-market:MO00809":{"sku":"LMD-000809","method":"review","score":0.7334,"ts":"2026-07-11T13:57:37Z"},"moda-market:MO00498":{"sku":"LMD-000498","method":"review","score":0.718,"ts":"2026-07-11T13:57:37Z"},"moda-market:MO00784":{"sku":"LMD-000784","method":"review","score":0.7056,"ts":"2026-07-11T13:57:37Z"},"style-hub:UST00025":{"sku":"LMD-000400","method":"review","score":0.577,"ts":"2026-07-11T13:57:37Z"},"moda-market:MO00667":{"sku":"LMD-000667","method":"review","score":0.739,"ts":"2026-07-11T16:12:38Z"},"trend-api:TR00353":{"sku":"LMD-000353","method":"review","score":0.729,"ts":"2026-07-11T16:12:38Z"},"moda-market:MO00504":{"sku":"LMD-000504","method":"review","score":0.6958,"ts":"2026-07-11T16:12:38Z"},"trend-api:UTR00033":{"sku":"LMD-000843","method":"review","score":0.6079,"ts":"2026-07-11T16:12:38Z"},"moda-market:UMO00054":{"sku":"LMD-000564","method":"review","score":0.5781,"ts":"2026-07-11T16:12:38Z"}},"reviewed_total":3910}
