{"queue":[{"key":"moda-market:UMO00024","sku":"LMD-000770","score":0.5333,"queued_at":"2026-07-21T11:20:29Z"},{"key":"trend-api:UTR00048","sku":"LMD-000588","score":0.5311,"queued_at":"2026-07-21T11:20:29Z"},{"key":"moda-market:UMO00054","sku":"LMD-000839","score":0.5264,"queued_at":"2026-07-21T11:20:29Z"},{"key":"moda-market:UMO00026","sku":"LMD-000515","score":0.5243,"queued_at":"2026-07-21T11:20:29Z"},{"key":"trend-api:UTR00019","sku":"LMD-000148","score":0.5241,"queued_at":"2026-07-21T11:20:29Z"},{"key":"trend-api:UTR00031","sku":"LMD-000076","score":0.5148,"queued_at":"2026-07-21T11:20:29Z"},{"key":"trend-api:UTR00066","sku":"LMD-000298","score":0.514,"queued_at":"2026-07-21T11:20:29Z"},{"key":"moda-market:UMO00023","sku":"LMD-000389","score":0.5131,"queued_at":"2026-07-21T11:20:29Z"},{"key":"moda-market:UMO00048","sku":"LMD-000701","score":0.5122,"queued_at":"2026-07-21T11:20:29Z"},{"key":"trend-api:UTR00001","sku":"LMD-000308","score":0.5119,"queued_at":"2026-07-21T11:20:29Z"},{"key":"moda-market:UMO00003","sku":"LMD-000216","score":0.5098,"queued_at":"2026-07-21T11:20:29Z"},{"key":"trend-api:UTR00067","sku":"LMD-000586","score":0.5095,"queued_at":"2026-07-21T11:20:29Z"},{"key":"style-hub:UST00013","sku":"LMD-000004","score":0.5093,"queued_at":"2026-07-19T16:13:54Z"},{"key":"moda-market:UMO00053","sku":"LMD-000875","score":0.5093,"queued_at":"2026-07-20T04:08:48Z"},{"key":"trend-api:UTR00061","sku":"LMD-000085","score":0.5056,"queued_at":"2026-07-21T11:20:29Z"},{"key":"moda-market:UMO00000","sku":"LMD-000240","score":0.505,"queued_at":"2026-07-20T04:08:48Z"},{"key":"style-hub:UST00034","sku":"LMD-000175","score":0.5049,"queued_at":"2026-07-21T03:50:56Z"},{"key":"moda-market:UMO00001","sku":"LMD-000112","score":0.5047,"queued_at":"2026-07-17T08:30:50Z"},{"key":"style-hub:UST00036","sku":"LMD-000756","score":0.5034,"queued_at":"2026-07-20T04:08:48Z"}],"confirmed":{"trend-api:TR00725":{"sku":"LMD-000725","method":"review","score":0.8045,"ts":"2026-07-15T03:40:31Z"},"trend-api:TR00675":{"sku":"LMD-000675","method":"review","score":0.8485,"ts":"2026-07-16T03:42:29Z"},"trend-api:TR00221":{"sku":"LMD-000221","method":"review","score":0.8026,"ts":"2026-07-16T03:42:29Z"},"moda-market:MO00332":{"sku":"LMD-000332","method":"review","score":0.738,"ts":"2026-07-16T16:44:14Z"},"moda-market:MO00224":{"sku":"LMD-000224","method":"review","score":0.7367,"ts":"2026-07-16T16:44:14Z"},"moda-market:MO00522":{"sku":"LMD-000522","method":"review","score":0.7354,"ts":"2026-07-16T16:44:14Z"},"moda-market:MO00046":{"sku":"LMD-000046","method":"review","score":0.7353,"ts":"2026-07-16T16:44:14Z"},"moda-market:MO00165":{"sku":"LMD-000165","method":"review","score":0.7343,"ts":"2026-07-16T16:44:14Z"},"moda-market:MO00359":{"sku":"LMD-000359","method":"review","score":0.7278,"ts":"2026-07-16T16:44:14Z"},"moda-market:MO00275":{"sku":"LMD-000275","method":"review","score":0.7164,"ts":"2026-07-16T16:44:14Z"},"moda-market:MO00526":{"sku":"LMD-000526","method":"review","score":0.7144,"ts":"2026-07-16T16:44:14Z"},"moda-market:MO00599":{"sku":"LMD-000599","method":"review","score":0.707,"ts":"2026-07-16T16:44:14Z"},"moda-market:MO00284":{"sku":"LMD-000284","method":"review","score":0.8402,"ts":"2026-07-17T03:42:07Z"},"moda-market:MO00197":{"sku":"LMD-000197","method":"review","score":0.7382,"ts":"2026-07-17T03:42:07Z"},"trend-api:TR00233":{"sku":"LMD-000233","method":"review","score":0.7364,"ts":"2026-07-17T03:42:07Z"},"moda-market:MO00253":{"sku":"LMD-000253","method":"review","score":0.7352,"ts":"2026-07-17T03:42:07Z"},"moda-market:MO00289":{"sku":"LMD-000289","method":"review","score":0.7288,"ts":"2026-07-17T03:42:07Z"},"trend-api:TR00375":{"sku":"LMD-000375","method":"review","score":0.7244,"ts":"2026-07-17T03:42:07Z"},"moda-market:MO00141":{"sku":"LMD-000141","method":"review","score":0.7238,"ts":"2026-07-17T03:42:07Z"},"moda-market:MO00431":{"sku":"LMD-000431","method":"review","score":0.7235,"ts":"2026-07-17T03:42:07Z"},"moda-market:MO00357":{"sku":"LMD-000357","method":"review","score":0.7231,"ts":"2026-07-17T03:42:07Z"},"moda-market:MO00562":{"sku":"LMD-000562","method":"review","score":0.7231,"ts":"2026-07-17T03:42:07Z"},"moda-market:MO00530":{"sku":"LMD-000530","method":"review","score":0.7184,"ts":"2026-07-17T03:42:07Z"},"moda-market:MO00269":{"sku":"LMD-000269","method":"review","score":0.7082,"ts":"2026-07-17T03:42:07Z"},"moda-market:MO00325":{"sku":"LMD-000325","method":"review","score":0.7013,"ts":"2026-07-17T03:42:07Z"},"moda-market:MO00715":{"sku":"LMD-000715","method":"review","score":0.7211,"ts":"2026-07-17T10:59:18Z"},"moda-market:MO00580":{"sku":"LMD-000580","method":"review","score":0.6917,"ts":"2026-07-17T16:36:11Z"},"moda-market:MO00646":{"sku":"LMD-000646","method":"review","score":0.7265,"ts":"2026-07-17T19:35:46Z"},"moda-market:MO00583":{"sku":"LMD-000583","method":"review","score":0.8162,"ts":"2026-07-18T03:37:31Z"},"moda-market:MO00504":{"sku":"LMD-000504","method":"review","score":0.8038,"ts":"2026-07-18T03:37:31Z"},"trend-api:TR00449":{"sku":"LMD-000449","method":"review","score":0.7848,"ts":"2026-07-18T03:37:31Z"},"moda-market:MO00852":{"sku":"LMD-000852","method":"review","score":0.7391,"ts":"2026-07-18T03:37:31Z"},"moda-market:MO00506":{"sku":"LMD-000506","method":"review","score":0.738,"ts":"2026-07-18T03:37:31Z"},"moda-market:MO00228":{"sku":"LMD-000228","method":"review","score":0.7334,"ts":"2026-07-18T03:37:31Z"},"moda-market:MO00498":{"sku":"LMD-000498","method":"review","score":0.7315,"ts":"2026-07-18T03:37:31Z"},"moda-market:MO00729":{"sku":"LMD-000729","method":"review","score":0.7255,"ts":"2026-07-18T03:37:31Z"},"moda-market:MO00012":{"sku":"LMD-000012","method":"review","score":0.7241,"ts":"2026-07-18T03:37:31Z"},"moda-market:MO00154":{"sku":"LMD-000154","method":"review","score":0.7237,"ts":"2026-07-18T03:37:31Z"},"moda-market:MO00247":{"sku":"LMD-000247","method":"review","score":0.7236,"ts":"2026-07-18T03:37:31Z"},"moda-market:MO00635":{"sku":"LMD-000635","method":"review","score":0.7229,"ts":"2026-07-18T03:37:31Z"},"moda-market:MO00538":{"sku":"LMD-000538","method":"review","score":0.6815,"ts":"2026-07-18T03:37:31Z"},"moda-market:MO00831":{"sku":"LMD-000831","method":"review","score":0.7698,"ts":"2026-07-18T08:11:46Z"},"moda-market:MO00784":{"sku":"LMD-000784","method":"review","score":0.718,"ts":"2026-07-18T13:53:24Z"},"moda-market:MO00133":{"sku":"LMD-000133","method":"review","score":0.7836,"ts":"2026-07-18T22:09:58Z"},"moda-market:MO00878":{"sku":"LMD-000878","method":"review","score":0.7009,"ts":"2026-07-18T22:09:58Z"},"moda-market:MO00762":{"sku":"LMD-000532","method":"review","score":0.8093,"ts":"2026-07-19T03:59:34Z"},"trend-api:TR00302":{"sku":"LMD-000302","method":"review","score":0.7377,"ts":"2026-07-19T03:59:34Z"},"moda-market:MO00799":{"sku":"LMD-000799","method":"review","score":0.7376,"ts":"2026-07-19T03:59:34Z"},"moda-market:MO00180":{"sku":"LMD-000180","method":"review","score":0.7372,"ts":"2026-07-19T03:59:34Z"},"moda-market:MO00568":{"sku":"LMD-000568","method":"review","score":0.7364,"ts":"2026-07-19T03:59:34Z"},"moda-market:MO00323":{"sku":"LMD-000323","method":"review","score":0.7362,"ts":"2026-07-19T03:59:34Z"},"trend-api:TR00199":{"sku":"LMD-000199","method":"review","score":0.7362,"ts":"2026-07-19T03:59:34Z"},"moda-market:MO00489":{"sku":"LMD-000489","method":"review","score":0.736,"ts":"2026-07-19T03:59:34Z"},"moda-market:MO00480":{"sku":"LMD-000480","method":"review","score":0.7351,"ts":"2026-07-19T03:59:34Z"},"moda-market:MO00660":{"sku":"LMD-000660","method":"review","score":0.7345,"ts":"2026-07-19T03:59:34Z"},"moda-market:MO00303":{"sku":"LMD-000303","method":"review","score":0.7182,"ts":"2026-07-19T03:59:34Z"},"trend-api:TR00859":{"sku":"LMD-000859","method":"review","score":0.7159,"ts":"2026-07-19T03:59:34Z"},"moda-market:MO00442":{"sku":"LMD-000442","method":"review","score":0.6887,"ts":"2026-07-19T03:59:34Z"},"moda-market:MO00265":{"sku":"LMD-000265","method":"review","score":0.6843,"ts":"2026-07-19T03:59:34Z"},"moda-market:MO00879":{"sku":"LMD-000879","method":"review","score":0.7486,"ts":"2026-07-19T10:46:06Z"},"moda-market:MO00030":{"sku":"LMD-000030","method":"review","score":0.7369,"ts":"2026-07-19T10:46:06Z"},"moda-market:MO00735":{"sku":"LMD-000735","method":"review","score":0.718,"ts":"2026-07-19T10:46:06Z"},"moda-market:MO00774":{"sku":"LMD-000774","method":"review","score":0.723,"ts":"2026-07-19T13:56:44Z"},"moda-market:MO00503":{"sku":"LMD-000503","method":"review","score":0.6995,"ts":"2026-07-19T13:56:44Z"},"style-hub:ST00820":{"sku":"LMD-000820","method":"review","score":0.8691,"ts":"2026-07-19T16:13:54Z"},"style-hub:ST00831":{"sku":"LMD-000831","method":"review","score":0.8256,"ts":"2026-07-19T16:13:54Z"},"style-hub:ST00871":{"sku":"LMD-000871","method":"review","score":0.7335,"ts":"2026-07-19T16:13:54Z"},"style-hub:UST00032":{"sku":"LMD-000551","method":"review","score":0.5556,"ts":"2026-07-19T16:13:54Z"},"moda-market:MO00276":{"sku":"LMD-000276","method":"review","score":0.718,"ts":"2026-07-19T19:35:57Z"},"moda-market:MO00810":{"sku":"LMD-000810","method":"review","score":0.7305,"ts":"2026-07-19T22:11:32Z"},"style-hub:ST00071":{"sku":"LMD-000071","method":"review","score":0.8621,"ts":"2026-07-20T04:08:48Z"},"style-hub:ST00206":{"sku":"LMD-000206","method":"review","score":0.8603,"ts":"2026-07-20T04:08:48Z"},"moda-market:MO00593":{"sku":"LMD-000593","method":"review","score":0.8429,"ts":"2026-07-20T04:08:48Z"},"moda-market:MO00594":{"sku":"LMD-000594","method":"review","score":0.7975,"ts":"2026-07-20T04:08:48Z"},"moda-market:MO00031":{"sku":"LMD-000031","method":"review","score":0.7907,"ts":"2026-07-20T04:08:48Z"},"moda-market:MO00825":{"sku":"LMD-000825","method":"review","score":0.7364,"ts":"2026-07-20T04:08:48Z"},"moda-market:MO00501":{"sku":"LMD-000501","method":"review","score":0.7359,"ts":"2026-07-20T04:08:48Z"},"style-hub:ST00004":{"sku":"LMD-000004","method":"review","score":0.734,"ts":"2026-07-20T04:08:48Z"},"moda-market:MO00724":{"sku":"LMD-000724","method":"review","score":0.733,"ts":"2026-07-20T04:08:48Z"},"moda-market:MO00106":{"sku":"LMD-000106","method":"review","score":0.7325,"ts":"2026-07-20T04:08:48Z"},"moda-market:MO00695":{"sku":"LMD-000695","method":"review","score":0.7322,"ts":"2026-07-20T04:08:48Z"},"moda-market:MO00286":{"sku":"LMD-000286","method":"review","score":0.7307,"ts":"2026-07-20T04:08:48Z"},"style-hub:ST00072":{"sku":"LMD-000072","method":"review","score":0.723,"ts":"2026-07-20T04:08:48Z"},"moda-market:MO00123":{"sku":"LMD-000123","method":"review","score":0.7216,"ts":"2026-07-20T04:08:48Z"},"moda-market:MO00134":{"sku":"LMD-000134","method":"review","score":0.7191,"ts":"2026-07-20T04:08:48Z"},"moda-market:MO00802":{"sku":"LMD-000802","method":"review","score":0.718,"ts":"2026-07-20T04:08:48Z"},"style-hub:ST00625":{"sku":"LMD-000625","method":"review","score":0.7175,"ts":"2026-07-20T04:08:48Z"},"moda-market:MO00673":{"sku":"LMD-000673","method":"review","score":0.7164,"ts":"2026-07-20T04:08:48Z"},"moda-market:MO00644":{"sku":"LMD-000644","method":"review","score":0.7083,"ts":"2026-07-20T04:08:48Z"},"moda-market:MO00557":{"sku":"LMD-000557","method":"review","score":0.7055,"ts":"2026-07-20T04:08:48Z"},"moda-market:MO00232":{"sku":"LMD-000232","method":"review","score":0.718,"ts":"2026-07-20T09:38:02Z"},"moda-market:MO00700":{"sku":"LMD-000700","method":"review","score":0.6911,"ts":"2026-07-20T09:38:02Z"},"trend-api:TR00875":{"sku":"LMD-000875","method":"review","score":0.7378,"ts":"2026-07-20T14:35:17Z"},"moda-market:MO00749":{"sku":"LMD-000749","method":"review","score":0.7176,"ts":"2026-07-20T14:35:17Z"},"moda-market:UMO00027":{"sku":"LMD-000558","method":"review","score":0.6322,"ts":"2026-07-20T14:35:17Z"},"moda-market:MO00315":{"sku":"LMD-000315","method":"review","score":0.7334,"ts":"2026-07-20T16:46:08Z"},"moda-market:MO00021":{"sku":"LMD-000021","method":"review","score":0.6823,"ts":"2026-07-20T16:46:08Z"},"style-hub:UST00009":{"sku":"LMD-000091","method":"review","score":0.6716,"ts":"2026-07-20T16:46:08Z"},"moda-market:MO00681":{"sku":"LMD-000681","method":"review","score":0.6955,"ts":"2026-07-20T19:59:11Z"},"moda-market:MO00065":{"sku":"LMD-000065","method":"review","score":0.7771,"ts":"2026-07-20T22:15:13Z"},"moda-market:MO00740":{"sku":"LMD-000740","method":"review","score":0.7384,"ts":"2026-07-20T22:15:13Z"},"moda-market:MO00406":{"sku":"LMD-000406","method":"review","score":0.7362,"ts":"2026-07-20T22:15:13Z"},"moda-market:MO00023":{"sku":"LMD-000023","method":"review","score":0.718,"ts":"2026-07-20T22:15:13Z"},"style-hub:ST00284":{"sku":"LMD-000284","method":"review","score":0.8782,"ts":"2026-07-21T03:50:56Z"},"style-hub:ST00556":{"sku":"LMD-000556","method":"review","score":0.8496,"ts":"2026-07-21T03:50:56Z"},"moda-market:MO00071":{"sku":"LMD-000071","method":"review","score":0.8036,"ts":"2026-07-21T03:50:56Z"},"moda-market:MO00090":{"sku":"LMD-000090","method":"review","score":0.735,"ts":"2026-07-21T03:50:56Z"},"moda-market:MO00690":{"sku":"LMD-000690","method":"review","score":0.7325,"ts":"2026-07-21T03:50:56Z"},"moda-market:MO00533":{"sku":"LMD-000533","method":"review","score":0.7293,"ts":"2026-07-21T03:50:56Z"},"moda-market:MO00268":{"sku":"LMD-000268","method":"review","score":0.7271,"ts":"2026-07-21T03:50:56Z"},"moda-market:MO00411":{"sku":"LMD-000411","method":"review","score":0.7257,"ts":"2026-07-21T03:50:56Z"},"moda-market:MO00459":{"sku":"LMD-000459","method":"review","score":0.7236,"ts":"2026-07-21T03:50:56Z"},"moda-market:MO00461":{"sku":"LMD-000461","method":"review","score":0.7229,"ts":"2026-07-21T03:50:56Z"},"moda-market:MO00609":{"sku":"LMD-000609","method":"review","score":0.713,"ts":"2026-07-21T03:50:56Z"},"moda-market:MO00451":{"sku":"LMD-000451","method":"review","score":0.7128,"ts":"2026-07-21T03:50:56Z"},"moda-market:MO00797":{"sku":"LMD-000797","method":"review","score":0.7093,"ts":"2026-07-21T03:50:56Z"},"moda-market:MO00088":{"sku":"LMD-000088","method":"review","score":0.7076,"ts":"2026-07-21T03:50:56Z"},"style-hub:ST00127":{"sku":"LMD-000127","method":"review","score":0.7034,"ts":"2026-07-21T03:50:56Z"},"moda-market:MO00664":{"sku":"LMD-000664","method":"review","score":0.6962,"ts":"2026-07-21T03:50:56Z"},"moda-market:UMO00033":{"sku":"LMD-000264","method":"review","score":0.6564,"ts":"2026-07-21T03:50:56Z"},"style-hub:UST00017":{"sku":"LMD-000777","method":"review","score":0.603,"ts":"2026-07-21T03:50:56Z"},"moda-market:MO00335":{"sku":"LMD-000335","method":"review","score":0.718,"ts":"2026-07-21T09:04:25Z"},"moda-market:MO00367":{"sku":"LMD-000367","method":"review","score":0.7083,"ts":"2026-07-21T09:04:25Z"},"moda-market:MO00697":{"sku":"LMD-000697","method":"review","score":0.7009,"ts":"2026-07-21T09:04:25Z"},"moda-market:MO00245":{"sku":"LMD-000245","method":"review","score":0.7314,"ts":"2026-07-21T11:20:29Z"},"moda-market:MO00793":{"sku":"LMD-000793","method":"review","score":0.7287,"ts":"2026-07-21T11:20:29Z"},"moda-market:MO00258":{"sku":"LMD-000258","method":"review","score":0.718,"ts":"2026-07-21T14:27:44Z"},"style-hub:UST00008":{"sku":"LMD-000313","method":"review","score":0.5678,"ts":"2026-07-21T14:27:44Z"},"moda-market:MO00078":{"sku":"LMD-000078","method":"review","score":0.7305,"ts":"2026-07-21T16:47:07Z"},"moda-market:MO00571":{"sku":"LMD-000571","method":"review","score":0.7127,"ts":"2026-07-21T16:47:07Z"},"moda-market:MO00578":{"sku":"LMD-000578","method":"review","score":0.6988,"ts":"2026-07-21T16:47:07Z"},"trend-api:UTR00029":{"sku":"LMD-000222","method":"review","score":0.5825,"ts":"2026-07-21T16:47:07Z"},"moda-market:UMO00017":{"sku":"LMD-000900","method":"review","score":0.595,"ts":"2026-07-21T19:55:31Z"}},"reviewed_total":6663}
